CHANGELOG.txt
LICENCE.txt
MANIFEST.in
README.txt
setup.py
rajakdrk/__init__.py
rajakdrk.egg-info/PKG-INFO
rajakdrk.egg-info/SOURCES.txt
rajakdrk.egg-info/dependency_links.txt
rajakdrk.egg-info/top_level.txt