Metadata-Version: 2.1
Name: rajakdrk
Version: 0.0.1
Summary: My full details.
Home-page: 
Author: Rajak Dudekula (Mr.drk)
Author-email: mrdrkofficial@gmail.com
License: MIT
Keywords: portfolio rajakdrk mrdrk
Classifier: Development Status :: 5 - Production/Stable
Classifier: Intended Audience :: Education
Classifier: Operating System :: Microsoft :: Windows :: Windows 10
Classifier: License :: OSI Approved :: MIT License
Classifier: Programming Language :: Python :: 3
License-File: LICENCE.txt
